{
  "title": "ReviewMaster - Tech Reviews & Comparisons",
  "description": "Expert tech reviews, in-depth comparisons, and buying guides to help you make informed tech decisions",
  "sections": [
    {
      "title": "styles",
      "id": "styles",
      "type": "html",
      "resetable": true,
      "data": []
    },
    {
      "title": "navigation",
      "id": "navigation",
      "type": "template",
      "resetable": true,
      "data": [
        "blog_title",
        "blog_logo",
        "navigation"
      ]
    },
    {
      "title": "posts_content",
      "id": "posts_content",
      "type": "template",
      "resetable": true,
      "data": []
    },
    {
      "title": "footer",
      "id": "footer",
      "type": "html",
      "resetable": true,
      "data": []
    }
  ]
}